accelrotate.py
accelrotate-1.0.0.dist-info/entry_points.txt
accelrotate-1.0.0.dist-info/WHEEL
accelrotate-1.0.0.dist-info/METADATA
accelrotate-1.0.0.dist-info/RECORD
